vkpybot/__init__.py
vkpybot/bot.py
vkpybot/events.py
vkpybot/servers.py
vkpybot/sessions.py
vkpybot/types.py
vkpybot/utils.py
vkpybot-0.2.0.dist-info/METADATA
vkpybot-0.2.0.dist-info/WHEEL
vkpybot-0.2.0.dist-info/LICENSE.txt
vkpybot-0.2.0.dist-info/RECORD
